{"data":{"site":{"siteMetadata":{"author":{"name":"Publee","bio":"Publee's velog","photo":"/images/publee.png","contacts":{"github":"publizm","instagram":"_publee","email":"publizm@gmail.com"}},"menu":[{"label":"Articles","path":"/"},{"label":"Categories","path":"/categories"},{"label":"About me","path":"/pages/about"},{"label":"Contact me","path":"/pages/contacts"}],"url":"https://publizm.github.io/","title":"Publee's velog","subtitle":"Publee's velog","copyright":"@ALL rights reserved.","disqusShortname":"publee"}}}}